batch6_musigma/__init__.py
batch6_musigma/grok_chat.py
batch6_musigma-1.0.0.dist-info/METADATA
batch6_musigma-1.0.0.dist-info/WHEEL
batch6_musigma-1.0.0.dist-info/top_level.txt
batch6_musigma-1.0.0.dist-info/RECORD
